setuptools_test/__init__.py
setuptools_test-0.0.2.dist-info/METADATA
setuptools_test-0.0.2.dist-info/RECORD
setuptools_test-0.0.2.dist-info/WHEEL
setuptools_test-0.0.2.dist-info/top_level.txt
