Metadata-Version: 2.1
Name: setuptools-test
Version: 0.0.2
Summary: Testing packaging with Python 3
Home-page: https://github.com/pypa/sampleproject
Author: Sheel Dandekar
Author-email: sheel_dandekar@intuit.com
License: UNKNOWN
Platform: UNKNOWN
